claude_history_backup/__init__.py
claude_history_backup/cli.py
claude_history_backup-0.3.0.dist-info/METADATA
claude_history_backup-0.3.0.dist-info/WHEEL
claude_history_backup-0.3.0.dist-info/entry_points.txt
claude_history_backup-0.3.0.dist-info/RECORD
