Metadata-Version: 2.4
Name: claude-history-backup
Version: 0.3.0
Summary: Backup and manage Claude Code session history
Author-email: Warren Zhu <wzhu@college.harvard.edu>
License: MIT
Keywords: backup,claude,cli,history
Classifier: Development Status :: 4 - Beta
Classifier: Environment :: Console
Classifier: License :: OSI Approved :: MIT License
Classifier: Programming Language :: Python :: 3
Classifier: Programming Language :: Python :: 3.10
Classifier: Programming Language :: Python :: 3.11
Classifier: Programming Language :: Python :: 3.12
Requires-Python: >=3.10
Requires-Dist: rich>=13.0.0
Requires-Dist: typer>=0.9.0
